[
  {
    "id": 1,
    "utc": "UTC+12",
    "offset": 12
  },
  {
    "id": 2,
    "utc": "UTC+11",
    "offset": 11
  },
  {
    "id": 3,
    "utc": "UTC+10",
    "offset": 10
  },
  {
    "id": 4,
    "utc": "UTC+9",
    "offset": 9
  },
  {
    "id": 5,
    "utc": "UTC+8",
    "offset": 8
  },
  {
    "id": 6,
    "utc": "UTC+7",
    "offset": 7
  },
  {
    "id": 7,
    "utc": "UTC+6",
    "offset": 6
  },
  {
    "id": 8,
    "utc": "UTC+5",
    "offset": 5
  },
  {
    "id": 9,
    "utc": "UTC+4",
    "offset": 4
  },
  {
    "id": 10,
    "utc": "UTC+3",
    "offset": 3
  },
  {
    "id": 11,
    "utc": "UTC+2",
    "offset": 2
  },
  {
    "id": 12,
    "utc": "UTC+1",
    "offset": 1
  },
  {
    "id": 13,
    "utc": "UTC±0",
    "offset": 0
  },
  {
    "id": 14,
    "utc": "UTC-1",
    "offset": -1
  },
  {
    "id": 15,
    "utc": "UTC-2",
    "offset": -2
  },
  {
    "id": 16,
    "utc": "UTC-3",
    "offset": -3
  },
  {
    "id": 17,
    "utc": "UTC-4",
    "offset": -4
  },
  {
    "id": 18,
    "utc": "UTC-5",
    "offset": -5
  },
  {
    "id": 19,
    "utc": "UTC-6",
    "offset": -6
  },
  {
    "id": 20,
    "utc": "UTC-7",
    "offset": -7
  },
  {
    "id": 21,
    "utc": "UTC-8",
    "offset": -8
  },
  {
    "id": 22,
    "utc": "UTC-9",
    "offset": -9
  },
  {
    "id": 23,
    "utc": "UTC-10",
    "offset": -10
  },
  {
    "id": 24,
    "utc": "UTC-11",
    "offset": -11
  },
  {
    "id": 25,
    "utc": "UTC-12",
    "offset": -12
  }
]